<?xml version="1.0" encoding="utf-8" ?>
<dwsync>
<file name="header.png" server="C:/AppServ/www/developer/" local="130958848260000000" remote="130958848260000000" Dst="0" />
<file name="header_bg.png" server="C:/AppServ/www/developer/" local="130973959120000000" remote="130973959120000000" Dst="0" />
<file name="header_text.png" server="C:/AppServ/www/developer/" local="130973959380000000" remote="130973959380000000" Dst="0" />
<file name="box_left_officer.png" server="C:/AppServ/www/developer/" local="130958848340000000" remote="130958848340000000" Dst="0" />
<file name="footer.png" server="C:/AppServ/www/developer/" local="130958848340000000" remote="130958848340000000" Dst="0" />
<file name="box_right_about.png" server="C:/AppServ/www/developer/" local="130958848760000000" remote="130958848760000000" Dst="0" />
<file name="box_right_about_custom.png" server="C:/AppServ/www/developer/" local="130974247800000000" remote="130974247800000000" Dst="0" />
<file name="box_right_related_agencies_custom.png" server="C:/AppServ/www/developer/" local="130974257440000000" remote="130974257440000000" Dst="0" />
<file name="box_left_menu_button.png" server="C:/AppServ/www/developer/" local="130974256980000000" remote="130974256980000000" Dst="0" />
<file name="box_left_menu_top.png" server="C:/AppServ/www/developer/" local="130974255700000000" remote="130974255700000000" Dst="0" />
<file name="box_left_counter_custom.png" server="C:/AppServ/www/developer/" local="130974254140000000" remote="130974254140000000" Dst="0" />
<file name="Logo_Center.png" server="C:/AppServ/www/developer/" local="131089624023989870" remote="131089624020000000" Dst="0" />
</dwsync>